{
  "spec": "after logging in I can see in the browser debug tools:\n\nauth_token\tundefined\t\nauth_user\tundefined\n\nUpdate the frontend to match the API response\n\nAnd update the hints md file to say that the API is always the source of truth... so never change the API to match the frontend... if you need to then change the frontend to match the API",
  "commitMessage": "fix: update frontend auth to match API response format\n\n- Updated AuthResponse interface to match backend API response\n- Updated auth service to use access_token and user_id\n- Updated auth context to use correct response fields\n- Added API-first guidance to hints.md",
  "stats": {
    "inputTokens": 58841,
    "cacheWriteTokens": 0,
    "cacheReadTokens": 127134,
    "outputTokens": 2468,
    "totalTokens": null,
    "cost": 0.1887624,
    "currency": "gbp",
    "processingMillis": 70580,
    "git": {
      "filesChanged": 3,
      "insertions": 11,
      "deletions": 13,
      "linesChanged": 13,
      "testFilesChanged": 0,
      "testInsertions": 0,
      "testDeletions": 0,
      "testLinesChanged": 0
    }
  }
}